soundvectors.py
soundvectors-1.0.dist-info/LICENSE
soundvectors-1.0.dist-info/METADATA
soundvectors-1.0.dist-info/WHEEL
soundvectors-1.0.dist-info/top_level.txt
soundvectors-1.0.dist-info/RECORD
