Metadata-Version: 2.1
Name: soundvectors
Version: 1.0
Summary: Vectorizing Speech Sounds in Phonetic Transcription
Home-page: https://github.com/cldf-clts/soundvectors
Author: Arne Rubehn
Author-email: arne.rubehn@uni-passau.de
License: MIT
Project-URL: Bug Tracker, https://github.com/cldf-clts/soundvectors/issues
Keywords: linguistics,speech sounds,feature vectors,CLTS
Platform: any
Classifier: Development Status :: 5 - Production/Stable
Classifier: Intended Audience :: Developers
Classifier: Intended Audience :: Science/Research
Classifier: Natural Language :: English
Classifier: Operating System :: OS Independent
Classifier: Programming Language :: Python :: 3
Classifier: Programming Language :: Python :: 3.8
Classifier: Programming Language :: Python :: 3.9
Classifier: Programming Language :: Python :: 3.10
Classifier: Programming Language :: Python :: 3.11
Classifier: Programming Language :: Python :: 3.12
Classifier: Programming Language :: Python :: Implementation :: CPython
Classifier: Programming Language :: Python :: Implementation :: PyPy
Classifier: License :: OSI Approved :: Apache Software License
Requires-Python: >=3.8
License-File: LICENSE
Provides-Extra: dev
Requires-Dist: pyclts ; extra == 'dev'
Requires-Dist: cltoolkit ; extra == 'dev'
Requires-Dist: scikit-learn ; extra == 'dev'
Requires-Dist: seaborn ; extra == 'dev'
Requires-Dist: numpy ; extra == 'dev'
Requires-Dist: matplotlib ; extra == 'dev'
Requires-Dist: lingpy ; extra == 'dev'
Requires-Dist: build ; extra == 'dev'
Provides-Extra: test
Requires-Dist: pyclts ; extra == 'test'
Requires-Dist: linse ; extra == 'test'
Requires-Dist: pytest ; extra == 'test'
Requires-Dist: pytest-cov ; extra == 'test'
